laff/.DS_Store
laff/__init__.py
laff/fit_bat.py
laff/flarefinding/__init__.py
laff/flarefinding/algorithms/__init__.py
laff/flarefinding/algorithms/flare_checks.py
laff/flarefinding/algorithms/savitsky.py
laff/flarefinding/algorithms/sequential.py
laff/flarefinding/flarefinding.py
laff/laff.py
laff/lightcurve_import.py
laff/modelling/__init__.py
laff/modelling/fit_afterglow.py
laff/modelling/fit_flare.py
laff/utility/__init__.py
laff/utility/utility.py
laff-1.0.0.dist-info/METADATA
laff-1.0.0.dist-info/WHEEL
laff-1.0.0.dist-info/RECORD
