Metadata-Version: 2.1
Name: laff
Version: 1.0.0
Summary: GRB lightcurve flare and continuum fitter.
Author: Adam Hennessy
Author-email: ah724@leicester.ac.uk
Requires-Python: >=3.9,<3.13
Classifier: Programming Language :: Python :: 3
Classifier: Programming Language :: Python :: 3.9
Classifier: Programming Language :: Python :: 3.10
Classifier: Programming Language :: Python :: 3.11
Classifier: Programming Language :: Python :: 3.12
Requires-Dist: astropy (>=5.2.2,<6.0.0)
Requires-Dist: bottleneck (>=1.3.8,<2.0.0)
Requires-Dist: matplotlib (>=3.7.1,<4.0.0)
Requires-Dist: numpy (>=1.24.3,<2.0.0)
Requires-Dist: pandas (>=2.0.1,<3.0.0)
Requires-Dist: scipy (>=1.10.1,<2.0.0)
